tel/__init__.py
tel/__main__.py
tel/writer.py
tel-1.0.0.dist-info/METADATA
tel-1.0.0.dist-info/WHEEL
tel-1.0.0.dist-info/entry_points.txt
tel-1.0.0.dist-info/top_level.txt
tel-1.0.0.dist-info/RECORD
