Metadata-Version: 2.1
Name: tel
Version: 1.0.0
Summary: The tiny experiment library.
Home-page: https://github.com/mrdrozdov/tiny-experiment-lib
Author: Andrew Drozdov
Author-email: andrew@mrdrozdov.com
License: MIT
Platform: UNKNOWN
Classifier: License :: OSI Approved :: MIT License
Classifier: Programming Language :: Python :: 3
Classifier: Programming Language :: Python :: 3.7
